af3io/__init__.py
af3io/cli.py
af3io/confidences.py
af3io/confidences_eval.py
af3io/core.py
af3io/data.py
af3io/input.py
af3io/predictions.py
af3io-0.5.dist-info/licenses/LICENSE
af3io-0.5.dist-info/METADATA
af3io-0.5.dist-info/WHEEL
af3io-0.5.dist-info/entry_points.txt
af3io-0.5.dist-info/top_level.txt
af3io-0.5.dist-info/RECORD
