Metadata-Version: 2.4
Name: af3io
Version: 0.5
Summary: Utilities for AlphaFold 3 input/output files
Author-email: jurgjn <jurgjn@users.noreply.github.com>
Requires-Python: >=3.10
License-File: LICENSE
Requires-Dist: click
Requires-Dist: humanfriendly
Dynamic: license-file
